{
  "source": "auto.it",
  "status": "ok",
  "scraped_at": "2026-06-14T16:06:24+00:00",
  "schema": "cars_autoit_v1",
  "request_policy": {
    "delay_seconds": 25.0,
    "backoff_seconds": 120.0,
    "limit": 1,
    "pages_per_fuel": 1,
    "requests_count": 3,
    "download_images": true,
    "image_delay_seconds": 5.0,
    "image_dir": "assets/cars/autoit",
    "max_image_mb": 6.0
  },
  "image_stats": {
    "found": 1,
    "downloaded": 1,
    "errors": 0
  },
  "cars": [
    {
      "id": "autoit_e_04803eb47805",
      "brand": "Ferrari",
      "model": "Ferrari undefined",
      "version": "Modelli Ferrari Luce",
      "powertrain": "Modelli Ferrari Luce",
      "fuel": "elettrica",
      "fuel_code": "E",
      "category": "electric",
      "source_site": "auto.it",
      "source_url": "https://www.auto.it/marche/ferrari-fer/modelli/luce-3561",
      "scraped_at": "2026-06-14T16:06:19+00:00",
      "price_source": "autoit_listino_nuovo",
      "image_source_url": "https://www.motornet.it/img/loghi/FER.png",
      "image_source_host": "www.motornet.it",
      "power_kw": 0.0,
      "power_cv": 0,
      "battery_kwh": 122.0,
      "price_eur": 550000,
      "image_local_path": "assets/cars/autoit/autoit_e_04803eb47805.png",
      "image_bytes": 9843,
      "image_downloaded_at": "2026-06-14T16:06:24+00:00"
    }
  ],
  "errors": []
}
